dash_chat_components/Chat.py
dash_chat_components/ChatInput.py
dash_chat_components/ChatMessage.py
dash_chat_components/ChatMessageList.py
dash_chat_components/ChatMessageTyping.py
dash_chat_components/ChatSimple.py
dash_chat_components/__init__.py
dash_chat_components/_imports_.py
dash_chat_components/dash_chat_components.js
dash_chat_components/metadata.json
dash_chat_components/package-info.json
dash_chat_components-0.1.0.dist-info/LICENSE
dash_chat_components-0.1.0.dist-info/METADATA
dash_chat_components-0.1.0.dist-info/WHEEL
dash_chat_components-0.1.0.dist-info/top_level.txt
dash_chat_components-0.1.0.dist-info/RECORD
