Metadata-Version: 2.1
Name: dash-chat-components
Version: 0.1.0
Summary: Chat components for Plotly Dash
Home-page: https://github.com/andriiryzhkov/dash-chat-components
Author: Andrii Ryzhkov <andrii.ryzhkov@gmail.com>
License: MIT
Project-URL: Bug Reports, https://github.com/andriiryzhkov/dash-chat-components/issues
Project-URL: Source, https://github.com/andriiryzhkov/dash-chat-components.git
Classifier: Development Status :: 4 - Beta
Classifier: Framework :: Dash
Classifier: Topic :: Communications :: Chat
Classifier: License :: OSI Approved :: MIT License
Classifier: Operating System :: OS Independent
Classifier: Programming Language :: Python
Classifier: Programming Language :: Python :: 3.7
Classifier: Programming Language :: Python :: 3.8
Classifier: Programming Language :: Python :: 3.9
Classifier: Programming Language :: Python :: 3.10
Classifier: Programming Language :: Python :: 3.11
Requires-Python: >=3.7, <4
License-File: LICENSE
Requires-Dist: dash >=2.5.1
